LICENSE
MANIFEST.in
README.md
pyproject.toml
requirements.txt
setup.cfg
setup.py
meta_segment/__init__.py
meta_segment/automatic_mask_generator.py
meta_segment/build_sam.py
meta_segment/predictor.py
meta_segment.egg-info/PKG-INFO
meta_segment.egg-info/SOURCES.txt
meta_segment.egg-info/dependency_links.txt
meta_segment.egg-info/requires.txt
meta_segment.egg-info/top_level.txt
meta_segment/modeling/__init__.py
meta_segment/modeling/common.py
meta_segment/modeling/image_encoder.py
meta_segment/modeling/mask_decoder.py
meta_segment/modeling/prompt_encoder.py
meta_segment/modeling/sam.py
meta_segment/modeling/transformer.py
meta_segment/utils/__init__.py
meta_segment/utils/amg.py
meta_segment/utils/onnx.py
meta_segment/utils/transforms.py