Metadata-Version: 2.1
Name: meta-segment
Version: 0.1.0
Home-page: https://github.com/kadirnar/segment-anything-pip
Author: kadirnar
License: Apache-2.0
Requires-Python: >=3.8
Provides-Extra: all
Provides-Extra: dev
License-File: LICENSE
